prefsort/__init__.py
prefsort/core.py
prefsort-0.1.0.dist-info/AUTHORS.rst
prefsort-0.1.0.dist-info/LICENSE
prefsort-0.1.0.dist-info/METADATA
prefsort-0.1.0.dist-info/WHEEL
prefsort-0.1.0.dist-info/top_level.txt
prefsort-0.1.0.dist-info/RECORD
