Metadata-Version: 2.1
Name: prefsort
Version: 0.1.0
Summary: Sort a sequence, preferring some values
Home-page: https://github.com/jonathaneunice/prefsort
Author: Jonathan Eunice
Author-email: jonathan.eunice@gmail.com
License: Apache Software License 2.0
Keywords: prefsort
Platform: UNKNOWN
Classifier: Development Status :: 3 - Alpha
Classifier: Intended Audience :: Developers
Classifier: License :: OSI Approved :: Apache Software License
Classifier: Programming Language :: Python :: 3.6
Classifier: Programming Language :: Python :: 3.7
Classifier: Programming Language :: Python :: 3.8
Classifier: Programming Language :: Python :: Implementation :: CPython
Classifier: Topic :: Software Development :: Libraries :: Python Modules
